pyprune/__init__.py
pyprune/backtracking.py
pyprune/sudoku/__init__.py
pyprune/sudoku/benchmark.py
pyprune/sudoku/sudoku.py
pyprune/sudoku/sudoku.txt
pyprune/sudoku/utils.py
pyprune-0.1.13.dist-info/METADATA
pyprune-0.1.13.dist-info/WHEEL
pyprune-0.1.13.dist-info/licenses/LICENSE
pyprune-0.1.13.dist-info/RECORD
