Metadata-Version: 2.4
Name: pyprune
Version: 0.1.13
Summary: Backtracking algorithm for constraint satisfaction puzzles.
Author-email: Miguel Pereira <miguel.b.per@gmail.com>
License: MIT License
License-File: LICENSE
Requires-Python: >=3.11
Requires-Dist: numpy>=2.0.0
